linkedin_auto_scraper/__init__.py
linkedin_auto_scraper/main.py
linkedin_auto_scraper/utils/__init__.py
linkedin_auto_scraper/utils/utils.py
linkedin_auto_scraper-0.2.1.dist-info/entry_points.txt
linkedin_auto_scraper-0.2.1.dist-info/METADATA
linkedin_auto_scraper-0.2.1.dist-info/WHEEL
linkedin_auto_scraper-0.2.1.dist-info/RECORD
