Metadata-Version: 2.1
Name: linkedin-auto-scraper
Version: 0.2.1
Summary: A tool to scrape infomation of people in a particular based on their job title and location
Author: kenfelix
Author-email: Kmrapper.kf@gmail.com
Requires-Python: >=3.10,<4.0
Classifier: Programming Language :: Python :: 3
Classifier: Programming Language :: Python :: 3.10
Classifier: Programming Language :: Python :: 3.11
Requires-Dist: about-time (>=4.2.1,<5.0.0)
Requires-Dist: alive-progress (>=3.1.4,<4.0.0)
Requires-Dist: async-generator (>=1.10,<2.0)
Requires-Dist: attrs (>=23.1.0,<24.0.0)
Requires-Dist: black (>=23.7.0,<24.0.0)
Requires-Dist: certifi (>=2023.7.22,<2024.0.0)
Requires-Dist: charset-normalizer (>=3.2.0,<4.0.0)
Requires-Dist: click (>=8.1.6,<9.0.0)
Requires-Dist: colorama (>=0.4.6,<0.5.0)
Requires-Dist: commonmark (>=0.9.1,<0.10.0)
Requires-Dist: exceptiongroup (>=1.1.2,<2.0.0)
Requires-Dist: fake-useragent (>=1.2.1,<2.0.0)
Requires-Dist: grapheme (>=0.6.0,<0.7.0)
Requires-Dist: h11 (>=0.14.0,<0.15.0)
Requires-Dist: idna (>=3.4,<4.0)
Requires-Dist: isort (>=5.12.0,<6.0.0)
Requires-Dist: mypy-extensions (>=1.0.0,<2.0.0)
Requires-Dist: numpy (>=1.25.2,<2.0.0)
Requires-Dist: outcome (>=1.2.0,<2.0.0)
Requires-Dist: packaging (>=23.1,<24.0)
Requires-Dist: pandas (>=2.0.3,<3.0.0)
Requires-Dist: pathspec (>=0.11.2,<0.12.0)
Requires-Dist: platformdirs (>=3.10.0,<4.0.0)
Requires-Dist: pydantic (>=2.1.1,<3.0.0)
Requires-Dist: pygments (>=2.16.1,<3.0.0)
Requires-Dist: pysocks (>=1.7.1,<2.0.0)
Requires-Dist: python-dateutil (>=2.8.2,<3.0.0)
Requires-Dist: python-dotenv (>=1.0.0,<2.0.0)
Requires-Dist: pytz (>=2023.3,<2024.0)
Requires-Dist: requests (>=2.31.0,<3.0.0)
Requires-Dist: rich (>=13.5.2,<14.0.0)
Requires-Dist: selenium (>=4.11.2,<5.0.0)
Requires-Dist: shellingham (>=1.5.0.post1,<2.0.0)
Requires-Dist: six (>=1.16.0,<2.0.0)
Requires-Dist: sniffio (>=1.3.0,<2.0.0)
Requires-Dist: sortedcontainers (>=2.4.0,<3.0.0)
Requires-Dist: tomli (>=2.0.1,<3.0.0)
Requires-Dist: tqdm (>=4.66.0,<5.0.0)
Requires-Dist: trio (>=0.22.2,<0.23.0)
Requires-Dist: trio-websocket (>=0.10.3,<0.11.0)
Requires-Dist: typer (>=0.9.0,<0.10.0)
Requires-Dist: typing-extensions (>=4.7.1,<5.0.0)
Requires-Dist: urllib3 (>=2.0.4,<3.0.0)
Requires-Dist: webdriver-manager (>=4.0.0,<5.0.0)
Requires-Dist: wsproto (>=1.2.0,<2.0.0)
Requires-Dist: xlsxwriter (>=3.1.2,<4.0.0)
